[
    { "id": 1, "nombre": "Creacion de un Blog",  "precio": 200, "cantidad": 1, "descripcion": "MARKETING", "imagen": "./img/diseno1.jpg"},

    {  "id": 2, "nombre": "Curso de Copywriting", "precio": 150, "cantidad": 1, "descripcion": "MARKETING", "imagen": "./img/diseno2.jpg"},

    {  "id": 3, "nombre": "Curso Estrategias para CEO", "precio": 175, "cantidad": 1, "descripcion": "MARKETING", "imagen": "./img/diseno3.jpg"},

    {  "id": 4, "nombre": "Introduccion al Diseño", "precio": 250, "cantidad": 1, "descripcion": "DISEÑO",    "imagen": "./img/diseno1.jpg"},

    {  "id": 5, "nombre": "Curso de Illustrator",  "precio": 280, "cantidad": 1, "descripcion": "DISEÑO",    "imagen": "./img/diseno2.jpg"},

    {  "id": 6, "nombre": "Fundamentos del Diseño",  "precio": 300, "cantidad": 1, "descripcion": "DISEÑO",    "imagen": "./img/diseno3.jpg"},

    {  "id": 7, "nombre": "WordPress",  "precio": 100, "cantidad": 1, "descripcion": "DISEÑO",    "imagen": "./img/blogs1.png"},

    {  "id": 8, "nombre": "Prototipado",  "precio": 350, "cantidad": 1, "descripcion": "DISEÑO",    "imagen": "./img/diseno4.png"}

]
